simple_http_server_redis_session/__init__.py
simple_http_server_redis_session/http_session_redis_impl.py
simple_http_server_redis_session-0.3.0.dist-info/LICENSE
simple_http_server_redis_session-0.3.0.dist-info/METADATA
simple_http_server_redis_session-0.3.0.dist-info/WHEEL
simple_http_server_redis_session-0.3.0.dist-info/top_level.txt
simple_http_server_redis_session-0.3.0.dist-info/RECORD
