Metadata-Version: 2.1
Name: simple-http-server-redis-session
Version: 0.3.0
Summary: A redis session implementation for python-simple-http-server
Home-page: https://github.com/keijack/python-simple-http-server-redis-session
Author: Keijack
Author-email: keijack.wu@gmail.com
License: UNKNOWN
Platform: UNKNOWN
Classifier: Programming Language :: Python :: 3.7
Classifier: Programming Language :: Python :: 3.8
Classifier: Programming Language :: Python :: 3.9
Classifier: License :: OSI Approved :: MIT License
Classifier: Operating System :: OS Independent
Requires-Dist: redis
Requires-Dist: simple-http-server
